{
  "work_number": 12,
  "work_label": "Work 12",
  "folder": "Work 12",
  "title": "Craig Green Collection Black",
  "year": "2025",
  "materials": "Paper, Prints, Oil",
  "format": "Collage",
  "size": "21 cm x 14.4 cm",
  "location": "",
  "key": "work12",
  "page_count": 1,
  "source_meta_docx": "portfolio_compiled_works_metadata/Work 12/Meta.docx",
  "images": [
    {
      "filename": "work-12-craig-green-collection-black-01.jpg",
      "relative_path": "portfolio_compiled_works_metadata/Work 12/work-12-craig-green-collection-black-01.jpg",
      "width_px": 9500,
      "height_px": 14096,
      "aspect_ratio": 0.67395,
      "mode": "RGB",
      "dpi": [
        96,
        96
      ],
      "file_size_bytes": 8455390,
      "sequence": 1,
      "work_page": 1,
      "page_role": "equal-height spread image 1"
    },
    {
      "filename": "work-12-craig-green-collection-black-02.jpg",
      "relative_path": "portfolio_compiled_works_metadata/Work 12/work-12-craig-green-collection-black-02.jpg",
      "width_px": 9770,
      "height_px": 13915,
      "aspect_ratio": 0.70212,
      "mode": "RGB",
      "dpi": [
        96,
        96
      ],
      "file_size_bytes": 8275693,
      "sequence": 2,
      "work_page": 1,
      "page_role": "equal-height spread image 2"
    }
  ],
  "content_start_page": 15,
  "content_end_page": 15
}
